kd_search_mcp/__init__.py
kd_search_mcp/main.py
kd_search_mcp-0.1.0.dist-info/licenses/LICENSE
tests/test_main.py
kd_search_mcp-0.1.0.dist-info/METADATA
kd_search_mcp-0.1.0.dist-info/WHEEL
kd_search_mcp-0.1.0.dist-info/top_level.txt
kd_search_mcp-0.1.0.dist-info/RECORD
