Metadata-Version: 2.4
Name: kd-search-mcp
Version: 0.1.0
Summary: A FastMCP-based client that searches Kingdee developer resources.
Home-page: https://github.com/yourusername/kd-search-mcp
Author: Your Name
Author-email: Your Name <your.email@example.com>
License: MIT License
Project-URL: Homepage, https://github.com/yourusername/kd-search-mcp
Requires-Python: >=3.13
License-File: LICENSE
Requires-Dist: mcp[cli]>=1.21.0
Requires-Dist: httpx>=0.27.0
Dynamic: author
Dynamic: home-page
Dynamic: license-file
Dynamic: requires-python
